heracles/__init__.py
heracles/__main__.py
heracles/_version.py
heracles/cli.py
heracles/core.py
heracles/ducc.py
heracles/fields.py
heracles/healpy.py
heracles/io.py
heracles/mapper.py
heracles/mapping.py
heracles/notebook.py
heracles/progress.py
heracles/result.py
heracles/rich.py
heracles/transforms.py
heracles/twopoint.py
heracles/unmixing.py
heracles/catalog/__init__.py
heracles/catalog/array.py
heracles/catalog/base.py
heracles/catalog/filters.py
heracles/catalog/fits.py
heracles/dices/__init__.py
heracles/dices/io.py
heracles/dices/jackknife.py
heracles/dices/shrinkage.py
heracles/dices/utils.py
heracles-25.1.dist-info/METADATA
heracles-25.1.dist-info/WHEEL
heracles-25.1.dist-info/entry_points.txt
heracles-25.1.dist-info/licenses/COPYING
heracles-25.1.dist-info/licenses/COPYING.LESSER
heracles-25.1.dist-info/RECORD
