Metadata-Version: 2.4
Name: heracles
Version: 25.1
Summary: Harmonic-space statistics on the sphere
Project-URL: Documentation, https://heracles.readthedocs.io/
Project-URL: Homepage, https://github.com/heracles-ec/heracles
Project-URL: Issues, https://github.com/heracles-ec/heracles/issues
Author-email: Nicolas Tessore <n.tessore@ucl.ac.uk>
License-Expression: LGPL-3.0-or-later
License-File: COPYING
License-File: COPYING.LESSER
Classifier: Intended Audience :: Science/Research
Classifier: License :: OSI Approved :: GNU Lesser General Public License v3 or later (LGPLv3+)
Classifier: Operating System :: OS Independent
Classifier: Programming Language :: Python :: 3
Classifier: Programming Language :: Python :: 3 :: Only
Classifier: Programming Language :: Python :: 3.9
Classifier: Programming Language :: Python :: 3.10
Classifier: Programming Language :: Python :: 3.11
Classifier: Topic :: Scientific/Engineering :: Astronomy
Requires-Python: >=3.9
Requires-Dist: convolvecl
Requires-Dist: coroutines
Requires-Dist: fitsio
Requires-Dist: healpy
Requires-Dist: numba
Requires-Dist: numpy
Requires-Dist: scipy
Provides-Extra: all
Requires-Dist: ducc0; extra == 'all'
Requires-Dist: rich; extra == 'all'
Provides-Extra: docs
Requires-Dist: furo; extra == 'docs'
Requires-Dist: ipython; extra == 'docs'
Requires-Dist: matplotlib; extra == 'docs'
Requires-Dist: nbsphinx; extra == 'docs'
Requires-Dist: numpydoc; extra == 'docs'
Requires-Dist: sphinx; extra == 'docs'
Requires-Dist: sphinxcontrib-katex; extra == 'docs'
Provides-Extra: test
Requires-Dist: ducc0; extra == 'test'
Requires-Dist: pytest; extra == 'test'
Requires-Dist: pytest-cov; extra == 'test'
Requires-Dist: pytest-rerunfailures; extra == 'test'
